{
	"Edit": {
		"app_name": "EDIT.EXE",
		"category": "Applications",
		"genre": "Text Editor",
		"developer": "Microsoft",
		"publisher": "Microsoft",
		"year": 1991,
		"required_software": {
			"os": "dos"
		}
	},
	"QBasic": {
		"app_name": "QBASIC.EXE",
		"category": "Applications",
		"genre": "IDE",
		"subgenre": "Basic",
		"developer": "Microsoft",
		"publisher": "Microsoft",
		"year": 1991,
		"required_software": {
			"os": "dos"
		}
	},
	"robotfindskitten": {
		"app_name": "robotdos.exe",
		"category": "Games",
		"developer": "Leonard Richardson",
		"year": 1997,
		"min_players": 1,
		"max_players": 1,
		"controls": {
			"player_1": {
				"move_up": ["up_arrow", "dpad_up"],
				"move_down": ["down_arrow", "dpad_down"],
				"move_left": ["left_arrow", "dpad_left"],
				"move_right": ["right_arrow", "dpad_right"],
				"play_again": ["y", "primary_button"],
				"exit": ["n", "secondary_button"]
			}
		},
		"required_software": {
			"os": "dos"
		}
	},
	"Second Reality": {
		"app_name": "SECOND.EXE",
		"category": "Demos",
		"developer": "Future Crew",
		"year": 1993,
		"compat_notes": "486 CPU & VGA graphics recommended, Sound Blaster/SB Pro/GUS sound",
		"required_hardware": {
			"min_ram": 570000,
			"min_cpu": "386"
		},
		"required_software": {
			"os": "dos"
		}
	},
	"8088 Corruption": {
		"app_name": "8088_COR.EXE",
		"category": "Demos",
		"developer": "Hornet",
		"year": 2004,
		"compat_notes": "Sound Blaster Pro + Sound Blaster 2.0; designed for original IBM PC 5150 but may run on later",
		"required_hardware": {
			"max_graphics": "cga"
		},
		"required_software": {
			"os": "dos"
		}
	},
	"8088 Domination": {
		"app_name": "8088DOM.BAT",
		"category": "Demos",
		"developer": "Hornet",
		"year": 2014,
		"compat_notes": "Sound Blaster 1.5 or later; needs CGA graphics for composite colour effects",
		"required_hardware": {
			"max_graphics": "cga"
		},
		"required_software": {
			"os": "dos"
		}
	},
	"Arctic Adventure Episode 1": {
		"app_name": "AA1.EXE",
		"category": "Games",
		"required_software": {
			"os": "dos"
		},
		"developer": "Apogee Software",
		"publisher": "Apogee Software",
		"year": 1991
	},
	"Alien Carnage": {
		"app_name": "CARNAGE.EXE",
		"category": "Games",
		"notes": "Freeware release with patches from DOSBox team. Also known as Halloween Harry (1993), not sure if that would have a different exe? Joystick controls in case I decide to put those in the controls object: Movement as expected; button 1 = fire, button 2 = jetpack thrust, button 3 = cycle weapons, hold button 4 + up or down = pan camera. Toggle display is between radar (minimap) and weapons (ammo status)",
		"developer": "Interactive Binary Illusions/SubZero Software",
		"publisher": "Apogee Sotware",
		"year": 1994,
		"min_players": 1,
		"max_players": 1,
		"controls": {
			"player_1": {
				"flamethrower": ["1", null],
				"photon_cannon": ["2", null],
				"missiles": ["3", null],
				"grenades": ["4", null],
				"micro_nukes": ["5", null],
				"omegas": ["6", null],
				"cycle_weapons": ["space", "aux_primary_button"],
				"abort_game": ["escape", null],
				"save": ["f2", null],
				"restart_level": ["f10", null],
				"toggle_display": ["r", null],
				"toggle_turbo": ["t", null],
				"pause": ["p", "start"],
				"pan_camera_up": ["page_up", "right_stick_up"],
				"pan_camera_down": ["page_down", "right_stick_down"],
				"center_joystick": ["j", null],
				"toggle_music": ["m", null],
				"move_left": ["left_arrow", "dpad_left"],
				"move_right": ["right_arrow", "dpad_right"],
				"jump": ["up_arrow", "primary_button"],
				"duck": ["down_arrow", "dpad_down"],
				"jetpack_thrust": ["left_control", "aux_secondary_button"],
				"fire": ["left_alt", "secondary_button"],
				"help": ["f1", null]
			}
		},
		"compat_notes": "Recommends SB or SB Pro and 386 CPU; compatible with 2 or 4 button gamepad/joysticks and mouse",
		"required_hardware": {
			"min_ram": 573440,
			"min_cpu": "286",
			"min_graphics": "vga"
		},
		"required_software": {
			"os": "dos"
		}
	},
	"Bio Menace Episode 1": {
		"app_name": "menace1.bat",
		"category": "Games",
		"notes": "Command line options: /COMP (SVGA compatibility), /LATCHPEL (ATI SVGA compat), /NOAL (Don't detect adlib), /NOJOYS (Don't detect joystick), /NOMOUSE (don't detect mouse, which is only used for menus)",
		"developer": "Apogee Software",
		"publisher": "Apogee Software",
		"year": 1993,
		"min_players": 1,
		"max_players": 1,
		"controls": {
			"player_1": {}
		},
		"compat_notes": "Mentions incompatibility with memory managers and adding STACKS=9,128 to CONFIG.SYS if lockups happen; recommends MS-DOS 6",
		"required_software": {
			"os": "dos",
			"min_os_version": "3.3"
		}
	},
	"California Games": {
		"app_name": "CALGAMES.EXE",
		"category": "Games",
		"notes": "Ignore other .exe files in the game folder, those are individual game modes",
		"genre": "Sports",
		"subgenre": "Compilation",
		"required_software": {
			"os": "dos"
		},
		"developer": "Epyx",
		"publisher": "Epyx",
		"year": 1988
	},
	"California Games II": {
		"app_name": "CGII.EXE",
		"category": "Games",
		"genre": "Sports",
		"subgenre": "Compilation",
		"required_software": {
			"os": "dos"
		},
		"developer": "Epyx",
		"publisher": "Epyx",
		"year": 1990
	},
	"Dark Ages Episode 1": {
		"app_name": "DA1.EXE",
		"category": "Games",
		"compat_notes": "Uses Adlib sound, might work with other Adlib compatible sound cards too",
		"required_software": {
			"os": "dos"
		},
		"developer": "Scenario Software",
		"publisher": "Apogee Software",
		"year": 1991
	},
	"God of Thunder": {
		"app_name": "GOT.EXE",
		"category": "Games",
		"notes": "Joystick controls: Movement = stick, throw hammer = button 1, use magic item = button 2. Arrow keys are also used for item selection and responses in conversation. Command line options: /NOAL = Don't detect Adlib, /NOSB = Don't detect Sound Blaster, /NOJOY = Don't detect joystick",
		"min_players": 1,
		"max_players": 1,
		"controls": {
			"player_1": {
				"move_up": ["up_arrow", "dpad_up"],
				"move_down": ["down_arrow", "dpad_down"],
				"move_left": ["left_arrow", "dpad_left"],
				"move_right": ["right_arrow", "dpad_right"],
				"throw_hammer": ["left_alt", "aux_primary_button"],
				"use_magic_item": ["left_control", "secondary_button"],
				"display_items": ["space", "select"],
				"select_item": ["enter", "primary_button"],
				"die": ["d", "aux_secondary_button"]
			}
		},
		"compat_notes": "Original readme says Adlib for music and SB for sound effects",
		"required_hardware": {
			"min_ram": 522240,
			"min_cpu": "286",
			"max_cpu": "pentium",
			"min_graphics": "vga"
		},
		"required_software": {
			"os": "dos"
		},
		"developer": "Adept Software",
		"publisher": "Software Creations",
		"year": 1993
	},
	"Heros: The Sanguine Seven": {
		"app_name": "HEROS.EXE",
		"category": "Games",
		"required_hardware": {
			"for_xt": false
		},
		"required_software": {
			"os": "dos"
		},
		"developer": "Jeffrey Fullerton",
		"year": 1993
	},
	"I.M. Meen": {
		"app_name": "MEEN.BAT",
		"category": "Games",
		"required_software": {
			"os": "dos"
		},
		"developer": "Animation Magic",
		"publisher": "Simon & Schuster",
		"year": 1995,
		"genre": "Edutainment",
		"subgenre": "Literacy"
	},
	"Jazz Jackrabbit": {
		"app_name": "JAZZ.EXE",
		"category": "Games",
		"notes": "Name is presumably the same for shareware version and full version. Joystick controls: Movement = left/right, look up = up, duck = down, jump = button 1, fire = button 2, cycle weapons = button 3 (or up + button 2 on 2-button joysticks). Does joystick work for moving forward in bonus stages?",
		"min_players": 1,
		"max_players": 1,
		"controls": {
			"player_1": {
				"jump": ["left_alt", "primary_button"],
				"fire": ["space", "secondary_button"],
				"roll": ["space", "secondary_button"],
				"move_left": ["left_arrow", "dpad_left"],
				"move_right": ["right_arrow", "dpad_right"],
				"look_up": ["up_arow", "dpad_up"],
				"duck": ["down_arrow", "dpad_down"],
				"cycle_weapons": ["left_control", "aux_primary_button"],
				"menu": ["escape", "select"],
				"slow_motion": ["t", "left_shoulder"],
				"pause": ["p", "start"],
				"move_forward": ["up_arrow", "dpad_up"],
				"adjust_detail_level": ["f1", "right_shoulder"]
			}
		},
		"genre": "Run & Gun",
		"developer": "Epic MegaGames",
		"publisher": "Epic MegaGames",
		"year": 1994,
		"compat_notes": "Menus seem to stutter in DOSBox (fixed in DOSBox-X), in-game seems fine though.Needs SB, SB16, SB Pro, Pro Audio Spectrum, or GUS for sound. Apparently HIMEM.SYS or EMM386 can slow things down, but disabling EMS in DOSBox config doesn't fix the stuttering",
		"required_hardware": {
			"min_ram": 2621440,
			"min_cpu": "386",
			"min_cpu_speed": 33
		},
		"required_software": {
			"os": "dos"
		}
	},
	"Plumbers Don't Wear Ties": {
		"app_name": "SHOWTIME.EXE",
		"category": "Games",
		"min_players": 1,
		"max_players": 1,
		"genre": "Visual Novel",
		"subgenre": "Interactive (Multiple Ending)",
		"required_software": {
			"os": "dos"
		},
		"developer": "United Pixtures",
		"publisher": "United Pixtures",
		"year": 1993,
		"adult": true
	},
	"Castle of Kroz": {
		"app_name": "CASTLE.EXE",
		"category": "Games",
		"required_software": {
			"os": "dos"
		},
		"developer": "Apogee Software",
		"publisher": "Apogee Software",
		"year": 1990
	},
	"Caverns of Kroz": {
		"app_name": "CAVERNS.COM",
		"category": "Games",
		"required_software": {
			"os": "dos"
		},
		"developer": "Apogee Software",
		"publisher": "Apogee Software",
		"year": 1988
	},
	"Caverns of Kroz 2": {
		"app_name": "CAVERNS.EXE",
		"category": "Games",
		"required_software": {
			"os": "dos"
		},
		"developer": "Apogee Software",
		"publisher": "Apogee Software",
		"year": 1988
	},
	"Dungeons of Kroz": {
		"app_name": "DUNGEONS.COM",
		"category": "Games",
		"required_software": {
			"os": "dos"
		},
		"developer": "Apogee Software",
		"publisher": "Apogee Software",
		"year": 1989
	},
	"Hints for Kroz": {
		"app_name": "KROZHINT.EXE",
		"category": "Applications",
		"genre": "Game Utility",
		"subgenre": "Guide",
		"required_software": {
			"os": "dos"
		},
		"developer": "Apogee Software",
		"publisher": "Apogee Software"
	},
	"Kingdom of Kroz": {
		"app_name": "Kingdom.com",
		"category": "Games",
		"required_software": {
			"os": "dos"
		},
		"developer": "Apogee Software",
		"publisher": "Apogee Software",
		"year": 1987
	},
	"Kingdom of Kroz 2": {
		"app_name": "KINGDOM.EXE",
		"category": "Games",
		"required_software": {
			"os": "dos"
		},
		"developer": "Apogee Software",
		"publisher": "Apogee Software",
		"year": 1990
	},
	"The Lost Adventures of Kroz": {
		"app_name": "LOST.EXE",
		"category": "Games",
		"required_software": {
			"os": "dos"
		},
		"developer": "Apogee Software",
		"publisher": "Apogee Software",
		"year": 1990
	},
	"Shrine of Kroz": {
		"app_name": "SHRINE.EXE",
		"category": "Games",
		"required_software": {
			"os": "dos"
		},
		"developer": "Apogee Software",
		"publisher": "Apogee Software",
		"year": 1990
	},
	"The Final Crusade of Kroz": {
		"app_name": "CRUSADE.EXE",
		"category": "Games",
		"required_software": {
			"os": "dos"
		},
		"developer": "Apogee Software",
		"publisher": "Apogee Software",
		"year": 1990
	},
	"Return to Kroz": {
		"app_name": "RETURN.EXE",
		"category": "Games",
		"required_software": {
			"os": "dos"
		},
		"developer": "Apogee Software",
		"publisher": "Apogee Software",
		"year": 1990
	},
	"Temple of Kroz": {
		"app_name": "TEMPLE.EXE",
		"category": "Games",
		"required_software": {
			"os": "dos"
		},
		"developer": "Apogee Software",
		"publisher": "Apogee Software",
		"year": 1990
	},
	"Landmark System Speed Test (6.00)": {
		"app_name": "SPEED600.EXE",
		"category": "Applications",
		"notes": "Command line: /b = Don't show help, /nv = Don't do initial video test, /q = No sound, /xx = Run for xx seconds then exit, e.g. /40 = run for 40 seconds",
		"genre": "Benchmark",
		"required_software": {
			"os": "dos"
		},
		"developer": "Landmark Research",
		"publisher": "Landmark Research"
	},
	"The Adventures of Maddog Williams in The Dungeons of Duridian": {
		"app_name": "MDWVGA.EXE",
		"category": "Games",
		"genre": "Adventure",
		"notes": "Freeware version disables copy protection, you can respond to the wizard asking you about manual things with anything. Genre is weird, sort of RPG/graphical adventure hybrid",
		"min_players": 1,
		"max_players": 1,
		"required_software": {
			"os": "dos"
		},
		"developer": "Game Crafters",
		"publisher": "Game Crafters",
		"year": 1992
	},
	"Monuments of Mars Episode 1": {
		"app_name": "MARS1.EXE",
		"category": "Games",
		"required_software": {
			"os": "dos"
		},
		"developer": "Scenario Software",
		"publisher": "Apogee Software",
		"year": 1991
	},
	"One Must Fall: 2097": {
		"app_name": "OMF.EXE",
		"category": "Games",
		"notes": "Joystick controls: Jump = up, punch = button 1, kick = button 2, move left/right = left/right, kneel = down. Block by moving backwards. Might have local two-player?",
		"controls": {
			"player_1": {
				"jump": ["up_arrow", "dpad_up"],
				"move_left": ["left_arrow", "dpad_left"],
				"move_right": ["right_arrow", "dpad_right"],
				"kneel": ["down_arrow", "dpad_down"],
				"punch": ["return", "primary_button"],
				"kick": ["right_shift", "secondary_button"],
				"chat_mode": ["left_alt + c", null],
				"gameplay_options": ["left_alt + g", null]
			}
		},
		"genre": "Fighting",
		"subgenre": "Versus",
		"developer": "Diversions Entertainment",
		"publisher": "Epic MegaGames",
		"year": 1994,
		"compat_notes": "Modem, null modem cable, or IPX for network play; VGA graphics",
		"required_hardware": {
			"min_ram": 3670016,
			"min_cpu": "386",
			"min_graphics": "vga"
		},
		"required_software": {
			"os": "dos"
		}
	},
	"Raiders of the Forbidden Mine": {
		"app_name": "RAIDERS.EXE",
		"other_app_names": [
			"RAIDERS.COM"
		],
		"category": "Games",
		"notes": "Part of Adventure Fun-Pak. Also known as Raiders of the Lost Mine, Diamond Digger, and Gold Miner",
		"genre": "Maze",
		"subgenre": "Digging",
		"required_hardware": {
			"max_cpu_speed": 4.77,
			"for_xt": true
		},
		"required_software": {
			"os": "dos"
		},
		"publisher": "Apogee Software",
		"year": 1989
	},
	"Night Bomber": {
		"app_name": "BOMBER.COM",
		"category": "Games",
		"notes": "Part of Adventure Fun-Pak",
		"required_hardware": {
			"max_cpu_speed": 4.77,
			"for_xt": true
		},
		"required_software": {
			"os": "dos"
		},
		"publisher": "Apogee Software",
		"year": 1989
	},
	"Rogue Runner": {
		"app_name": "RUNNER.EXE",
		"other_app_names": [
			"RUNNER.COM"
		],
		"category": "Games",
		"genre": "Maze",
		"notes": "Part of Adventure Fun-Pak",
		"required_hardware": {
			"max_cpu_speed": 4.77,
			"for_xt": true
		},
		"required_software": {
			"os": "dos"
		},
		"publisher": "Apogee Software",
		"year": 1989
	},
	"The Thing": {
		"app_name": "THING.COM",
		"category": "Games",
		"clone_of": "Hunt the Wumpus",
		"notes": "Part of Adventure Fun-Pak",
		"required_hardware": {
			"max_cpu_speed": 4.77,
			"for_xt": true
		},
		"required_software": {
			"os": "dos"
		},
		"publisher": "Apogee Software",
		"year": 1989
	},
	"Asteroid Rescue": {
		"app_name": "ASTEROID.COM",
		"category": "Games",
		"notes": "Part of Puzzle Fun-Pak",
		"required_hardware": {
			"max_cpu_speed": 4.77,
			"for_xt": true
		},
		"required_software": {
			"os": "dos"
		},
		"publisher": "Apogee Software",
		"year": 1989
	},
	"Block Five": {
		"app_name": "BLOCK5.EXE",
		"other_app_names": [
			"BLOCK5.COM"
		],
		"category": "Games",
		"genre": "Tabletop",
		"subgenre": "Go",
		"notes": "Part of Puzzle Fun-Pak",
		"required_hardware": {
			"max_cpu_speed": 4.77,
			"for_xt": true
		},
		"required_software": {
			"os": "dos"
		},
		"publisher": "Apogee Software",
		"year": 1989
	},
	"Maze Machine": {
		"app_name": "MAZE.COM",
		"category": "Applications",
		"genre": "Non-Computer Game Generator",
		"notes": "Part of Puzzle Fun-Pak",
		"compat_notes": "Can send resulting maze to printer",
		"required_hardware": {
			"max_cpu_speed": 4.77,
			"for_xt": true
		},
		"required_software": {
			"os": "dos"
		},
		"publisher": "Apogee Software",
		"year": 1989
	},
	"Phrase Master": {
		"app_name": "PHRASE.EXE",
		"other_app_names": [
			"PHRASE.COM"
		],
		"category": "Games",
		"notes": "Part of Puzzle Fun-Pak",
		"min_players": 2,
		"max_players": 2,
		"required_hardware": {
			"max_cpu_speed": 4.77,
			"for_xt": true
		},
		"required_software": {
			"os": "dos"
		},
		"publisher": "Apogee Software",
		"year": 1989
	},
	"Radix: Beyond the Void": {
		"app_name": "RADIX.EXE",
		"category": "Games",
		"notes": "Numbers 1-7 used for weapon select",
		"min_players": 1,
		"max_players": 1,
		"controls": {
			"player_1": {
				"pull_up": ["up_arrow", "dpad_up"],
				"pull_down": ["down_arrow", "dpad_down"],
				"bank_left": ["left_arrow", "dpad_left"],
				"bank_right": ["right_arrow", "dpad_right"],
				"fire": ["left_control", "primary_button"],
				"plasma_bomb": ["space", "secondary_button"],
				"speed_up": ["right_shift", "left_stick_up"],
				"afterburner": ["/", "aux_secondary_button"],
				"strafe_mode": ["left_alt", "left_shoulder"],
				"back_view": ["return", "right_shoulder"],
				"toggle_leveling": [".", "select"],
				"switch_weapon": [",", "aux_primary_button"],
				"help": ["f1", null],
				"toggle_camera": ["f2", null],
				"save": ["f3", null],
				"load": ["f4", null],
				"adjust_detail_level": ["f5", null],
				"toggle_auto_adjust_detail": ["f6", null],
				"quick_save": ["f7", null],
				"toggle_auto_levelling": ["f8", null],
				"quick_load": ["f9", null],
				"gamma_correction": ["f10", null],
				"mission_objectives": ["f11", null],
				"increase_size": ["page_up", null],
				"decrease_size": ["page_down", null],
				"toggle_automap": ["tab", null],
				"menu": ["esc", null],
				"pause": ["pause_break", "start"]
			}
		},
		"genre": "Rail Shooter",
		"subgenre": "Flight",
		"compat_notes": "Recommends 66MHz and 8MB RAM; uses modem for network; also mouse controls",
		"required_hardware": {
			"min_ram": 4194304,
			"min_cpu": "486",
			"min_cpu_speed": 33,
			"min_graphics": "vga"
		},
		"required_software": {
			"os": "dos"
		},
		"developer": "Neural Storm Entertainment",
		"publisher": "Epic MegaGames",
		"year": 1995
	},
	"Sid Meier's Railroad Tycoon": {
		"app_name": "RRT.EXE",
		"category": "Games",
		"notes": "Freeware release (Deluxe 1.01) still includes copy protection referring to the manual, which is included as PDF",
		"genre": "Simulation",
		"required_hardware": {
			"min_ram": 655360,
			"min_cpu": "386",
			"min_cpu_speed": 16,
			"min_graphics": "vga"
		},
		"required_software": {
			"os": "dos",
			"min_os_version": "5.0"
		},
		"developer": "MicroProse",
		"publisher": "2K Games",
		"year": 1990
	},
	"Retro City Rampage": {
		"app_name": "RCR.EXE",
		"category": "Games",
		"notes": "Included with Steam version",
		"required_hardware": {
			"min_ram": 4194304,
			"min_cpu": "486"
		},
		"required_software": {
			"os": "dos"
		},
		"developer": "Vblank Entertainment",
		"publisher": "Vblank Entertainment",
		"year": 2015
	},
	"RMCobol": {
		"app_name": "RMCOBOL.EXE",
		"category": "Applications",
		"genre": "Compiler",
		"subgenre": "COBOL",
		"required_software": {
			"os": "dos"
		},
		"developer": "Micro Focus",
		"publisher": "Micro Focus"
	},
	"Sango Fighter": {
		"app_name": "SANGO.EXE",
		"category": "Games",
		"genre": "Fighting",
		"subgenre": "Versus",
		"required_software": {
			"os": "dos"
		},
		"developer": "Panda Entertainment",
		"publisher": "Super Fighter Team",
		"year": 2009
	},
	"Sango Fighter 2": {
		"app_name": "SANGO2.EXE",
		"category": "Games",
		"genre": "Fighting",
		"subgenre": "Versus",
		"required_software": {
			"os": "dos"
		},
		"developer": "Panda Entertainment",
		"publisher": "Super Fighter Team",
		"year": 2009
	},
	"The Simpsons": {
		"app_name": "SIMPSONS.BAT",
		"category": "Games",
		"notes": "Port of arcade game",
		"genre": "Beat'em up",
		"required_software": {
			"os": "dos"
		},
		"developer": "Novotrade",
		"publisher": "Konami",
		"year": 1991
	},
	"Supernova": {
		"app_name": "NOVA.COM",
		"category": "Games",
		"notes": "Includes source under GPL",
		"genre": "Adventure",
		"subgenre": "Text",
		"required_software": {
			"os": "dos"
		},
		"developer": "Apogee Software",
		"publisher": "Apogee Software",
		"year": 1987
	},
	"Major Stryker": {
		"app_name": "STRYKER.EXE",
		"category": "Games",
		"genre": "Shooter",
		"subgenre": "Vertical",
		"compat_notes": "EGA graphics",
		"required_software": {
			"os": "dos"
		},
		"developer": "Apogee Software",
		"publisher": "Apogee Software",
		"year": 1993
	},
	"Caves of Thor": {
		"app_name": "CAVES.EXE",
		"category": "Games",
		"genre": "Maze",
		"required_hardware": {
			"for_xt": true
		},
		"required_software": {
			"os": "dos"
		},
		"developer": "Scenario Software",
		"publisher": "Apogee Software",
		"year": 1989
	},
	"Beyond the Titanic": {
		"app_name": "BEYOND.COM",
		"category": "Games",
		"notes": "Includes source under GPL",
		"genre": "Adventure",
		"subgenre": "Text",
		"compat_notes": "Needs a floppy drive to save",
		"required_software": {
			"os": "dos"
		},
		"developer": "Apogee Software",
		"publisher": "Apogee Software",
		"year": 1986
	},
	"Pharaoh's Tomb Episode 1": {
		"app_name": "PTOMB1.EXE",
		"category": "Games",
		"notes": "Freeware (3.0)",
		"required_software": {
			"os": "dos"
		},
		"developer": "Micro F/X Software",
		"publisher": "Apogee Software",
		"year": 1990
	},
	"Trivia Whiz Volume 1": {
		"app_name": "TW1.EXE",
		"category": "Games",
		"genre": "Quiz",
		"required_hardware": {
			"for_xt": true
		},
		"required_software": {
			"os": "dos"
		},
		"developer": "Micro F/X Software",
		"publisher": "Apogee Software",
		"year": 1988
	},
	"Word Whiz Volume 1": {
		"app_name": "WW1.EXE",
		"category": "Games",
		"notes": "Includes GPL source",
		"genre": "Quiz",
		"required_hardware": {
			"for_xt": true
		},
		"required_software": {
			"os": "dos"
		},
		"developer": "Apogee Software",
		"publisher": "Apogee Software",
		"year": 1988
	},
	"Stargunner": {
		"app_name": "STARGUN.EXE",
		"category": "Games",
		"notes": "Joystick controls: Movement = up/down/left/right, fire = button 1, nuke = button 2 ",
		"min_players": 1,
		"max_players": 1,
		"controls": {
			"player_1": {
				"move_up": ["up_arrow", "dpad_up"],
				"move_down": ["down_arrow", "dpad_down"],
				"move_left": ["left_arrow", "dpad_left"],
				"move_right": ["right_arrow", "dpad_right"],
				"fire": ["left_control", "primary_button"],
				"nuke": ["left_alt", "secondary_button"],
				"pause": ["pause_break", "start"],
				"quit": ["escape", null],
				"help": ["f1", null],
				"save": ["f2", null],
				"load": ["f3", null],
				"controls": ["f4", null],
				"sound": ["f5", null],
				"quick_save": ["f6", null],
				"quick_load": ["f9", null],
				"fast_exit": ["f10", null],
				"brightness": ["f11", null],
				"screenshot": ["print_screen", null]
			}
		},
		"genre": "Shooter",
		"subgenre": "Horizontal",
		"compat_notes": "SB/GUS/PAS sound, SVGA w/1MB VRAM & Pentium @ 90MHz w/ 16MB RAM recommended",
		"required_hardware": {
			"min_ram": 8388608,
			"min_cpu": "486",
			"min_graphics": "vga"
		},
		"required_software": {
			"os": "dos"
		},
		"developer": "WizardWorks",
		"publisher": "Apogee Software",
		"year": 1996
	},
	"Supaplex (Speed Fix 6.3)": {
		"app_name": "spfix63.exe",
		"category": "Games",
		"clone_of": "Boulder Dash",
		"notes": "Command line: *(10) to *(0): Set speed from slowest to fastest; *: Run at fastest speed; !(n): Use level set n; /(n): Enter level n without going through menu; &(n): Use player n; #: Set all levels playable as though they were skipped without touching player list or high scores; s: Shake screen for all explosions; n: Never shake screen; d: Force debug mode; m: Noclip in debug mode; c: Create level file if deleted; w: Use only SAVEGAME.SAV as saved game; e: Force EGA mode; h: Force original horizontal smooth scroll timing; r: Refresh video memory at end of each game; o: Record using original demo name; t: Allow original infinite dynamite cheat",
		"min_players": 1,
		"max_players": 1,
		"controls": {
			"player_1": {
				"move_up": ["up_arrow", "dpad_up"],
				"move_down": ["down_arrow", "dpad_down"],
				"move_left": ["left_arrow", "dpad_left"],
				"move_right": ["right_arrow", "dpad_right"],
				"drop_dynamite": ["space", "primary_button"],
				"eat": ["space", "secondary_button"],
				"exit": ["escape", null],
				"exit_completely": ["left_alt + x", null],
				"display_dynamite_count": ["right_shift", "aux_primary_button"],
				"recalibrate_joystick": ["j", null],
				"pause": ["p", "start"],
				"quick_save": ["left_control + w", null],
				"quick_load": ["left_control + l", null]
			}
		},
		"genre": "Maze",
		"subgenre": "Digging",
		"required_software": {
			"os": "dos"
		},
		"developer": "Think!Ware Development",
		"publisher": "Digital Integration",
		"year": 1991
	},
	"Arctic Adventure Episode 2": {
		"parent": "Arctic Adventure Episode 1",
		"app_name": "AA2.EXE"
	},
	"Arctic Adventure Episode 3": {
		"parent": "Arctic Adventure Episode 1",
		"app_name": "AA3.EXE"
	},
	"Arctic Adventure Episode 4": {
		"parent": "Arctic Adventure Episode 1",
		"app_name": "AA4.EXE"
	},
	"Bio Menace Episode 2": {
		"parent": "Bio Menace Episode 1",
		"app_name": "menace2.bat"
	},
	"Bio Menace Episode 3": {
		"parent": "Bio Menace Episode 1",
		"app_name": "menace3.bat"
	},
	"Dark Ages Episode 2": {
		"parent": "Dark Ages Episode 1",
		"app_name": "DA2.EXE"
	},
	"Dark Ages Episode 3": {
		"parent": "Dark Ages Episode 1",
		"app_name": "DA3.EXE"
	},
	"Monuments of Mars Episode 2": {
		"parent": "Monuments of Mars Episode 1",
		"app_name": "MARS2.EXE"
	},
	"Monuments of Mars Episode 3": {
		"parent": "Monuments of Mars Episode 1",
		"app_name": "MARS3.EXE"
	},
	"Monuments of Mars Episode 4": {
		"parent": "Monuments of Mars Episode 1",
		"app_name": "MARS4.EXE"
	},
	"Realm of Thor": {
		"parent": "Caves of Thor",
		"app_name": "REALM.EXE",
		"notes": "Episode 2 of Apogee Thor trilogy"
	},
	"Thor's Revenge": {
		"parent": "Caves of Thor",
		"app_name": "REVENGE.EXE",
		"notes": "Episode 3 of Apogee Thor trilogy"
	},
	"Pharaoh's Tomb Episode 2": {
		"parent": "Pharaoh's Tomb Episode 1",
		"app_name": "PTOMB2.EXE"
	},
	"Pharaoh's Tomb Episode 3": {
		"parent": "Pharaoh's Tomb Episode 1",
		"app_name": "PTOMB3.EXE"
	},
	"Pharaoh's Tomb Episode 4": {
		"parent": "Pharaoh's Tomb Episode 1",
		"app_name": "PTOMB4.EXE"
	},
	"Trivia Whiz Volume 2": {
		"parent": "Trivia Whiz Volume 1",
		"app_name": "TW2.EXE"
	},
	"Trivia Whiz Volume 3": {
		"parent": "Trivia Whiz Volume 1",
		"app_name": "TW3.EXE"
	},
	"Trivia Whiz Volume 4": {
		"parent": "Trivia Whiz Volume 1",
		"app_name": "TW4.EXE"
	},
	"Trivia Whiz Volume 5": {
		"parent": "Trivia Whiz Volume 1",
		"app_name": "TW5.EXE"
	},
	"Word Whiz Volume 2": {
		"parent": "Word Whiz Volume 1",
		"app_name": "WW2.EXE"
	},
	"Word Whiz Volume 3": {
		"parent": "Word Whiz Volume 1",
		"app_name": "WW3.EXE"
	},
	"Word Whiz Volume 4": {
		"parent": "Word Whiz Volume 1",
		"app_name": "WW4.EXE"
	},
	"AdLib Juke Box": {
		"app_name": "JUKEBOX.EXE",
		"category": "Applications",
		"genre": "Music Player",
		"developer": "AdLib",
		"publisher": "AdLib",
		"year": 1987
	},
	"Arcade Volleyball": {
		"app_name": "Av.exe",
		"category": "Games",
		"genre": "Sports",
		"subgenre": "Volleyball",
		"notes": "CGA graphics. Now released as public domain",
		"min_players": 1,
		"max_players": 2,
		"developer": "Rhett Anderson",
		"year": 1988
	},
	"Electro Man": {
		"app_name": "EM.EXE",
		"category": "Games",
		"notes": "2006 CC-BY-SA 2.5 release; recompiled from source specifically for DOSBox usage. Can also use F10 for return to menu",
		"controls": {
			"player_1": {
				"move_left": ["left_arrow", "dpad_left"],
				"move_right": ["right_arrow", "dpad_right"],
				"jump": ["up_arrow", "primary_button"],
				"fire": ["space", "secondary_button"],
				"activate_teleport": ["down_arrow", "aux_primary_button"],
				"exit": ["left_alt + x", null],
				"return_to_menu": ["escape", null],
				"save": ["f2", null],
				"load": ["f3", null]
			}
		},
		"developer": "xLand Games",
		"publisher": "xLand Games",
		"year": 2006
	},
	"Adventures of Robbo": {
		"app_name": "ROBBO.EXE",
		"category": "Games",
		"notes": "2006 CC-BY-SA 2.5 release; recompiled from source specifically for DOSBox usage. Space/fire also starts game from title screen",
		"controls": {
			"player_1": {
				"move_left": ["left_arrow", "dpad_left"],
				"move_right": ["right_arrow", "dpad_right"],
				"move_up": ["up_arrow", "dpad_up"],
				"move_down": ["down_arrow", "dpad_down"],
				"fire": ["space", "primary_button"],
				"enter_level_code": ["f3", null],
				"exit": ["left_alt + x", null],
				"return_to_title": ["f10", null],
				"die": ["escape", null],
				"toggle_sound": ["f1", null]
			}
		},
		"developer": "xLand Games",
		"publisher": "xLand Games",
		"year": 2006
	},
	"Heartlight PC": {
		"app_name": "HL.EXE",
		"category": "Games",
		"notes": "2006 CC-BY-SA 2.5 release; recompiled from source specifically for DOSBox usage. Space + left/right arrow changes level",
		"controls": {
			"player_1": {
				"move_left": ["left_arrow", "dpad_left"],
				"move_right": ["right_arrow", "dpad_right"],
				"move_up": ["up_arrow", "dpad_up"],
				"move_down": ["down_arrow", "dpad_down"],
				"start_game": ["space", "primary_button"],
				"exit": ["left_alt + x", null],
				"return_to_title": ["f10", null],
				"restart_level": ["escape", null],
				"toggle_music": ["f6", null],
				"toggle_sound": ["f7", null]
			}
		},
		"developer": "xLand Games",
		"publisher": "xLand Games",
		"year": 2006
	},
	"Atomic Tetris": {
		"app_name": "AT.EXE",
		"category": "Games",
		"clone_of": "Tetris",
		"min_players": 2,
		"max_players": 1,
		"controls": {
			"player_1": {
				"move_left": ["r", "dpad_left"],
				"move_right": ["y", "dpad_right"],
				"turn": ["t", "primary_button"],
				"drop": ["g", "dpad_down"],
				"quick_drop": ["1", "secondary_button"]
			},
			"player_2": {
				"move_left": ["4_numpad", "dpad_left"],
				"move_right": ["6_numpad", "dpad_right"],
				"turn": ["5_numpad", "primary_button"],
				"drop": ["2_numpad", "dpad_down"],
				"quick_drop": ["\\", "secondary_button"]
			}
		},
		"developer": "Jared Tarbell",
		"year": 1991
	},
	"Catacombs": {
		"app_name": "CATACOMB.EXE",
		"category": "Games",
		"developer": "John Carmack",
		"publisher": "SoftDisk",
		"year": 1991,
		"notes": "Part of Gamer's Edge sampler",
		"required_software": {
			"os": "dos"
		}
	},
	"Dangerous Dave": {
		"app_name": "DAVE.EXE",
		"other_app_names": [],
		"category": "Games",
		"genre": "Platform",
		"subgenre": "2D",
		"developer": "John Romero",
		"publisher": "SoftDisk",
		"year": 1991,
		"notes": "Part of Gamer's Edge sampler",
		"required_software": {
			"os": "dos"
		}
	},
	"Mega Man X (demo)": {
		"app_name": "MMXDEMO.EXE",
		"category": "Trials",
		"genre": "Run & Gun",
		"developer": "Rozner Labs",
		"publisher": "Capcom",
		"year": 1995,
		"required_software": {
			"os": "dos"
		}
	},
	"Mortal Kombat 3 (demo)": {
		"app_name": "MK3.EXE",
		"category": "Trials",
		"genre": "Fighting",
		"subgenre": "Versus",
		"developer": "Midway",
		"publisher": "GT Interactive",
		"year": 1996,
		"required_software": {
			"os": "dos"
		}
	},
	"Zool (demo)": {
		"app_name": "MNBV.EXE",
		"category": "Trials",
		"genre": "Platform",
		"subgenre": "2D",
		"developer": "Gremlin Graphics",
		"publisher": "Gremlin Graphics",
		"year": 1993,
		"required_software": {
			"os": "dos"
		}
	},
	"Tetris": {
		"app_name": "Tetris.exe",
		"category": "Games",
		"genre": "Puzzle",
		"subgenre": "Drop",
		"developer": "Vadim Gerasimov",
		"year": 1986,
		"notes": "The OG Tetris (other than the Elektronika 60 prototype)",
		"required_software": {
			"os": "dos"
		}
	},
	"Snarf": {
		"app_name": "snarf.exe",
		"category": "Games",
		"developer": "Everett Kaser",
		"year": 1993,
		"required_software": {
			"os": "dos"
		}
	},
	"The Lion King (demo)": {
		"app_name": "LIONKING.EXE",
		"category": "Trials",
		"developer": "East Point Software",
		"publisher": "Virgin",
		"year": 1994,
		"required_software": {
			"os": "dos"
		}
	},
	"Clyde's Revenge": {
		"app_name": "REVENGE.EXE",
		"category": "Games",
		"developer": "Moonlite Software",
		"publisher": "Moonlite Software",
		"year": 1995,
		"required_software": {
			"os": "dos"
		}
	},
	"Chopper Commando": {
		"app_name": "CHOPPER2.EXE",
		"category": "Games",
		"developer": "Mark Currie",
		"year": 2014,
		"notes": "Bug fixed version (v2.57) from Classic DOS Games",
		"required_software": {
			"os": "dos"
		}
	},
	"Clyde's Adventure Episode 1": {
		"app_name": "CLYDE1.EXE",
		"category": "Games",
		"developer": "Moonlite Software",
		"publisher": "Moonlite Software",
		"year": 1992,
		"required_software": {
			"os": "dos"
		}
	},
	"Clyde's Adventure Episode 2": {
		"app_name": "CLYDE2.EXE",
		"parent": "Clyde's Adventure Episode 1"
	},
	"Cyberdogs": {
		"app_name": "DOGS.EXE",
		"category": "Games",
		"developer": "Ronny Wester",
		"year": 1994,
		"required_software": {
			"os": "dos"
		}
	},
	"Cybersphere": {
		"app_name": "CYBER.EXE",
		"category": "Games",
		"developer": "Psycon Software",
		"publisher": "Psycon Software",
		"year": 1996,
		"clone_of": "Breakout",
		"required_software": {
			"os": "dos"
		}
	},
	"Cybersphere Plus": {
		"app_name": "CYBPLUS.EXE",
		"category": "Games",
		"developer": "Psycon Software",
		"publisher": "Psycon Software",
		"year": 1997,
		"clone_of": "Breakout",
		"required_software": {
			"os": "dos"
		}
	},
	"Duel 2000": {
		"app_name": "DUEL.EXE",
		"category": "Games",
		"developer": "Damon Hastings",
		"year": 1991,
		"required_software": {
			"os": "dos"
		}
	},
	"Jill of the Jungle Episode 1": {
		"app_name": "JILL.EXE",
		"category": "Games",
		"developer": "Epic MegaGames",
		"publisher": "Epic MegaGames",
		"year": 1992,
		"required_software": {
			"os": "dos"
		}
	},
	"Jump 'n' Bump": {
		"app_name": "jumpbump.exe",
		"category": "Games",
		"developer": "Brainchild Design",
		"publisher": "Brainchild Design",
		"year": 1998,
		"required_software": {
			"os": "dos"
		}
	},
	"Keen Dreams": {
		"app_name": "KDREAMS.EXE",
		"category": "Games",
		"developer": "id Software",
		"publisher": "SoftDisk",
		"year": 1992,
		"required_software": {
			"os": "dos"
		}
	},
	"Cool Spot (demo)": {
		"app_name": "SPOT.EXE",
		"category": "Trials",
		"developer": "Virgin",
		"publisher": "Virgin",
		"year": 1994,
		"required_software": {
			"os": "dos"
		}
	},
	"Abuse": {
		"app_name": "ABUSE.EXE",
		"category": "Games",
		"developer": "Cracked Dot Com",
		"publisher": "Electronic Arts",
		"year": 1996,
		"required_software": {
			"os": "dos"
		}
	},
	"Backlash": {
		"app_name": "BL.EXE",
		"category": "Games",
		"developer": "Sanctuary Software Studio",
		"publisher": "Sanctuary Software Studio",
		"year": 1994,
		"required_software": {
			"os": "dos"
		}
	},
	"Amulets and Armor": {
		"app_name": "AA.BAT",
		"category": "Games",
		"genre": "RPG",
		"subgenre": "Action RPG",
		"developer": "United Software Artists",
		"publisher": "United Software Artists",
		"year": 1997,
		"notes": "Re-released as freeware in 2013 by original developers (as Exiguus Entertainment)",
		"required_software": {
			"os": "dos"
		}
	},
	"Wolfenstein 3D": {
		"app_name": "WOLF3D.EXE",
		"category": "Games",
		"genre": "Shooter",
		"subgenre": "FPS",
		"year": 1992,
		"developer": "id Software",
		"publisher": "Apogee Software",
		"required_software": {
			"os": "dos"
		}
	},
	"Wolfenstein 3D (shareware)": {
		"parent": "Wolfenstein 3D",
		"category": "Trials"
	},
	"Wacky Wheels": {
		"app_name": "WW.EXE",
		"category": "Games",
		"genre": "Driving",
		"subgenre": "Kart",
		"year": 1994,
		"developer": "Beavis Soft",
		"publisher": "Apogee Software",
		"required_software": {
			"os": "dos"
		}
	},
	"The Incredible Machine (demo)": {
		"app_name": "TIM.EXE",
		"category": "Trials",
		"genre": "Puzzle",
		"year": 1993,
		"developer": "Jeff Tunnell",
		"publisher": "Sierra",
		"required_software": {
			"os": "dos"
		}
	},
	"The Incredible Machine 2 (demo)": {
		"app_name": "TIM2.EXE",
		"category": "Trials",
		"genre": "Puzzle",
		"year": 1994,
		"developer": "Jeff Tunnell",
		"publisher": "Sierra",
		"required_software": {
			"os": "dos"
		}
	},
	"Bust-a-Move Again (demo)": {
		"app_name": "BM2.EXE",
		"category": "Trials",
		"year": 1996,
		"developer": "Taito",
		"publisher": "Acclaim",
		"notes": "Can use CD of Saturn version for audio, but not required",
		"required_software": {
			"os": "dos"
		}
	},
	"X-Men: Children of the Atom (demo)": {
		"app_name": "XMENPC.EXE",
		"category": "Trials",
		"year": 1997,
		"developer": "Capcom",
		"publisher": "Acclaim",
		"required_software": {
			"os": "dos"
		}
	},
	"AstroFire": {
		"app_name": "astro.exe",
		"category": "Games",
		"year": 1994,
		"developer": "ORT Software",
		"publisher": "ORT Software",
		"required_software": {
			"os": "dos"
		}
	},
	"Aladdin (demo)": {
		"app_name": "ALADDIN.EXE",
		"category": "Trials",
		"year": 1994,
		"developer": "Virgin",
		"publisher": "Virgin",
		"required_software": {
			"os": "dos"
		}
	},
	"Mortal Kombat II (demo)": {
		"app_name": "MKII.EXE",
		"category": "Trials",
		"year": 1994,
		"developer": "Probe Software",
		"publisher": "Acclaim",
		"required_software": {
			"os": "dos"
		}
	},
	"Xenophage: Alien Bloodsport": {
		"app_name": "XPRX.EXE",
		"category": "Games",
		"genre": "Fighting",
		"subgenre": "Versus",
		"year": 1996,
		"developer": "Argo Games",
		"publisher": "Apogee Software",
		"required_hardware": {
			"min_cpu": "486DX",
			"min_cpu_speed": 33,
			"min_graphics": "vga",
			"min_ram": 8388608
		},
		"notes": "Recommends 486DX @ 66MHz, 16MB RAM, SVGA; uses 4-button gamepad or 2x 2-button joysticks",
		"required_software": {
			"os": "dos"
		},
		"controls": {
			"player_1": {
				"jump": ["up_arrow", "dpad_up"],
				"crouch": ["down_arrow", "dpad_down"],
				"move_left": ["left_arrow", "dpad_left"],
				"move_right": ["right_arrow", "dpad_right"],
				"weak_punch": ["left_control", "primary_button"],
				"weak_kick": ["left_alt", "secondary_button"],
				"strong_punch": ["left_shift", "aux_primary_button"],
				"strong_kick": ["z", "aux_secondary_button"],
				"jump_left": ["home", null],
				"jump_right": ["page_up", null],
				"crouch_left": ["end", null],
				"crouch_right": ["page_down", null]
			}
		}
	}	
}

